[
    {
        "Product_name": "Бизнес",
        "Action": "Removed from cart",
        "Time": "August 12th 2020, 8:59:09 pm"
    },
    {
        "Product_name": "Стандарт",
        "Action": "Added to cart",
        "Time": "August 12th 2020, 8:59:11 pm"
    },
    {
        "Product_name": "Базовый",
        "Action": "Added to cart",
        "Time": "August 12th 2020, 8:59:13 pm"
    },
    {
        "Product_name": "Стандарт",
        "Action": "Removed from cart",
        "Time": "August 12th 2020, 9:32:11 pm"
    },
    {
        "Product_name": "Базовый",
        "Action": "Removed from cart",
        "Time": "August 12th 2020, 9:32:13 pm"
    },
    {
        "Product_name": "Стандарт",
        "Action": "Added to cart",
        "Time": "August 12th 2020, 9:32:14 pm"
    },
    {
        "Product_name": "Базовый",
        "Action": "Added to cart",
        "Time": "August 12th 2020, 9:32:16 pm"
    },
    {
        "Product_name": "Базовый",
        "Action": "Changed data in cart",
        "Time": "August 12th 2020, 9:35:14 pm"
    },
    {
        "Product_name": "Стандарт",
        "Action": "Changed data in cart",
        "Time": "August 12th 2020, 9:35:17 pm"
    },
    {
        "Product_name": "Стандарт",
        "Action": "Changed data in cart",
        "Time": "August 12th 2020, 9:35:19 pm"
    },
    {
        "Product_name": "Базовый",
        "Action": "Changed data in cart",
        "Time": "August 12th 2020, 9:36:46 pm"
    },
    {
        "Product_name": "Бизнес",
        "Action": "Added to cart",
        "Time": "August 12th 2020, 9:36:48 pm"
    },
    {
        "Product_name": "Бизнес",
        "Action": "Removed from cart",
        "Time": "August 12th 2020, 9:36:51 pm"
    },
    {
        "Product_name": "Базовый",
        "Action": "Changed data in cart",
        "Time": "August 12th 2020, 9:37:14 pm"
    },
    {
        "Product_name": "Стандарт",
        "Action": "Changed data in cart",
        "Time": "August 12th 2020, 9:37:18 pm"
    },
    {
        "Product_name": "Стандарт",
        "Action": "Changed data in cart",
        "Time": "August 12th 2020, 9:37:18 pm"
    },
    {
        "Product_name": "Стандарт",
        "Action": "Changed data in cart",
        "Time": "August 12th 2020, 9:37:19 pm"
    },
    {
        "Product_name": "Базовый",
        "Action": "Changed data in cart",
        "Time": "August 12th 2020, 9:38:40 pm"
    },
    {
        "Product_name": "Стандарт",
        "Action": "Changed data in cart",
        "Time": "August 12th 2020, 9:38:41 pm"
    },
    {
        "Product_name": "Базовый",
        "Action": "Changed data in cart",
        "Time": "August 12th 2020, 9:39:52 pm"
    },
    {
        "Product_name": "Стандарт",
        "Action": "Changed data in cart",
        "Time": "August 12th 2020, 9:39:55 pm"
    },
    {
        "Product_name": "Бизнес",
        "Action": "Added to cart",
        "Time": "August 12th 2020, 9:39:58 pm"
    },
    {
        "Product_name": "Стандарт",
        "Action": "Changed data in cart",
        "Time": "August 12th 2020, 9:40:59 pm"
    },
    {
        "Product_name": "Стандарт",
        "Action": "Changed data in cart",
        "Time": "August 12th 2020, 9:41:00 pm"
    },
    {
        "Product_name": "Базовый",
        "Action": "Changed data in cart",
        "Time": "August 12th 2020, 9:41:02 pm"
    },
    {
        "Product_name": "Базовый",
        "Action": "Changed data in cart",
        "Time": "August 12th 2020, 9:41:03 pm"
    },
    {
        "Product_name": "Базовый",
        "Action": "Changed data in cart",
        "Time": "August 12th 2020, 9:41:04 pm"
    },
    {
        "Product_name": "Базовый",
        "Action": "Changed data in cart",
        "Time": "August 12th 2020, 9:41:05 pm"
    },
    {
        "Product_name": "Базовый",
        "Action": "Changed data in cart",
        "Time": "August 12th 2020, 9:41:06 pm"
    },
    {
        "Product_name": "Базовый",
        "Action": "Removed from cart",
        "Time": "August 12th 2020, 9:41:06 pm"
    },
    {
        "Product_name": "Базовый",
        "Action": "Added to cart",
        "Time": "August 12th 2020, 9:41:49 pm"
    },
    {
        "Product_name": "Стандарт",
        "Action": "Changed data in cart",
        "Time": "August 12th 2020, 9:42:12 pm"
    },
    {
        "Product_name": "Базовый",
        "Action": "Removed from cart",
        "Time": "August 12th 2020, 9:44:27 pm"
    },
    {
        "Product_name": "Стандарт",
        "Action": "Changed data in cart",
        "Time": "August 12th 2020, 9:44:30 pm"
    },
    {
        "Product_name": "Бизнес",
        "Action": "Removed from cart",
        "Time": "August 12th 2020, 9:47:08 pm"
    },
    {
        "Product_name": "Стандарт",
        "Action": "Changed data in cart",
        "Time": "August 12th 2020, 9:47:10 pm"
    },
    {
        "Product_name": "Базовый",
        "Action": "Added to cart",
        "Time": "August 12th 2020, 9:47:13 pm"
    },
    {
        "Product_name": "Бизнес",
        "Action": "Added to cart",
        "Time": "August 12th 2020, 9:50:12 pm"
    },
    {
        "Product_name": "Базовый",
        "Action": "Removed from cart",
        "Time": "August 12th 2020, 9:51:24 pm"
    },
    {
        "Product_name": "Стандарт",
        "Action": "Changed data in cart",
        "Time": "August 12th 2020, 9:51:25 pm"
    },
    {
        "Product_name": "Базовый",
        "Action": "Added to cart",
        "Time": "August 12th 2020, 9:51:27 pm"
    },
    {
        "Product_name": "Базовый",
        "Action": "Changed data in cart",
        "Time": "August 12th 2020, 9:52:50 pm"
    },
    {
        "Product_name": "Базовый",
        "Action": "Changed data in cart",
        "Time": "August 12th 2020, 9:52:54 pm"
    },
    {
        "Product_name": "Базовый",
        "Action": "Changed data in cart",
        "Time": "August 12th 2020, 9:53:33 pm"
    },
    {
        "Product_name": "Базовый",
        "Action": "Changed data in cart",
        "Time": "August 12th 2020, 9:53:36 pm"
    },
    {
        "Product_name": "Базовый",
        "Action": "Changed data in cart",
        "Time": "August 12th 2020, 9:54:06 pm"
    },
    {
        "Product_name": "Базовый",
        "Action": "Changed data in cart",
        "Time": "August 12th 2020, 9:54:08 pm"
    },
    {
        "Product_name": "Бизнес",
        "Action": "Removed from cart",
        "Time": "August 12th 2020, 9:54:09 pm"
    },
    {
        "Product_name": "Базовый",
        "Action": "Changed data in cart",
        "Time": "August 12th 2020, 9:54:46 pm"
    },
    {
        "Product_name": "Стандарт",
        "Action": "Changed data in cart",
        "Time": "August 12th 2020, 9:54:49 pm"
    },
    {
        "Product_name": "Бизнес",
        "Action": "Added to cart",
        "Time": "August 12th 2020, 9:54:50 pm"
    },
    {
        "Product_name": "Базовый",
        "Action": "Changed data in cart",
        "Time": "August 12th 2020, 9:55:19 pm"
    },
    {
        "Product_name": "Стандарт",
        "Action": "Changed data in cart",
        "Time": "August 12th 2020, 10:03:04 pm"
    },
    {
        "Product_name": "Стандарт",
        "Action": "Changed data in cart",
        "Time": "August 12th 2020, 10:03:04 pm"
    },
    {
        "Product_name": "Стандарт",
        "Action": "Removed from cart",
        "Time": "August 12th 2020, 10:03:05 pm"
    },
    {
        "Product_name": "Стандарт",
        "Action": "Added to cart",
        "Time": "August 12th 2020, 10:03:08 pm"
    },
    {
        "Product_name": "Базовый",
        "Action": "Changed data in cart",
        "Time": "August 12th 2020, 10:03:09 pm"
    },
    {
        "Product_name": "Базовый",
        "Action": "Changed data in cart",
        "Time": "August 12th 2020, 10:06:31 pm"
    },
    {
        "Product_name": "Базовый",
        "Action": "Changed data in cart",
        "Time": "August 12th 2020, 10:06:31 pm"
    },
    {
        "Product_name": "Базовый",
        "Action": "Changed data in cart",
        "Time": "August 12th 2020, 10:07:29 pm"
    },
    {
        "Product_name": "Базовый",
        "Action": "Changed data in cart",
        "Time": "August 12th 2020, 10:07:34 pm"
    },
    {
        "Product_name": "Базовый",
        "Action": "Changed data in cart",
        "Time": "August 12th 2020, 10:07:34 pm"
    }
]